cusum
