Metadata-Version: 2.1
Name: cusum
Version: 0.1.16
Summary: Full cumulative sum processing for change detection
Home-page: 
Author: Antoine Pfefer
Author-email: 
License: MIT
Requires-Python: >=3.9
License-File: LICENCE
